<annotation>
	<folder>images</folder>
	<filename>97.jpg</filename>
	<path>/home/fajar/Downloads/labelImg/data/images/97.jpg</path>
	<source>
		<database>Unknown</database>
	</source>
	<size>
		<width>800</width>
		<height>600</height>
		<depth>3</depth>
	</size>
	<segmented>0</segmented>
	<object>
		<name>mask</name>
		<pose>Unspecified</pose>
		<truncated>1</truncated>
		<difficult>0</difficult>
		<bndbox>
			<xmin>342</xmin>
			<ymin>1</ymin>
			<xmax>617</xmax>
			<ymax>301</ymax>
		</bndbox>
	</object>
</annotation>
